xbitinfo-0.0.5.dist-info/METADATA
xbitinfo-0.0.5.dist-info/WHEEL
xbitinfo-0.0.5.dist-info/entry_points.txt
xbitinfo-0.0.5.dist-info/licenses/LICENSE
xbitinfo/__init__.py
xbitinfo/_py_bitinfo.py
xbitinfo/bitinformation_wrapper.jl
xbitinfo/bitround.py
xbitinfo/graphics.py
xbitinfo/julia_helpers.py
xbitinfo/save_compressed.py
xbitinfo/xbitinfo.py
xbitinfo-0.0.5.dist-info/RECORD
