Metadata-Version: 2.1
Name: xbitinfo
Version: 0.0.5
Summary: Retrieve information content and compress accordingly.
Keywords: xbitinfo
License: MIT license
Requires-Python: <3.14,>=3.11
Requires-Dist: dask
Requires-Dist: xarray
Requires-Dist: tqdm
Requires-Dist: numcodecs>=0.10.0
Requires-Dist: matplotlib>=3.9.0
Requires-Dist: prefect>=3.3.0
Requires-Dist: zarr
